DataStructure/__init__.py
DataStructure/linkedlist.py
DataStructure/node.py
DataStructure/queue.py
DataStructure/stack.py
DataStructure/tree.py
tests/__init__.py
tests/test_linkedlist.py
tests/test_queue.py
tests/test_stack.py
tests/test_tree.py
DataStructure-0.1.1.dist-info/LICENSE.txt
DataStructure-0.1.1.dist-info/METADATA
DataStructure-0.1.1.dist-info/WHEEL
DataStructure-0.1.1.dist-info/top_level.txt
DataStructure-0.1.1.dist-info/RECORD
