Metadata-Version: 2.1
Name: DataStructure
Version: 0.1.1
Summary: Package with several data structures implemented.
Home-page: https://github.com/ReinaldoDiasAbreu/DataStructure
Author: Reinaldo Junio Dias de Abreu
Author-email: reinaldodiasabreu@gmail.com
License: UNKNOWN
Platform: UNKNOWN
Classifier: Programming Language :: Python :: 3
Classifier: License :: OSI Approved :: MIT License
Classifier: Operating System :: OS Independent
Requires-Python: >=3.7
